README.md
setup.py
LaTeXCompiler.egg-info/PKG-INFO
LaTeXCompiler.egg-info/SOURCES.txt
LaTeXCompiler.egg-info/dependency_links.txt
LaTeXCompiler.egg-info/entry_points.txt
LaTeXCompiler.egg-info/requires.txt
LaTeXCompiler.egg-info/top_level.txt
latexcompiler/LC.py
latexcompiler/__init__.py
latexcompiler/utils/__init__.py
latexcompiler/utils/compile_tex_files.py