Metadata-Version: 2.1
Name: LaTeXCompiler
Version: 1.0
Summary: A program for compiling LaTeX files the convenient way by stashing the auxiliary files into a specified folder.
Home-page: https://github.com/amrane99/LatexCompiler
Author: Amin Ranem
Author-email: aminranem@googlemail.com
License: MIT
Download-URL: https://github.com/amrane99/LaTeXCompiler/archive/refs/tags/v1.0.tar.gz
Keywords: LaTeX,BibTeX,Python
Platform: UNKNOWN
Classifier: Development Status :: 5 - Production/Stable
Classifier: Intended Audience :: Developers
Classifier: Topic :: Software Development :: Build Tools
Classifier: License :: OSI Approved :: MIT License
